[
    {
        "name": "Lorem ipsum dolor sit amet, consect",
        "cards": [
            {
                "name": "Lorem",
                "description": "Lorem ipsum dolor sit amet, consectetur adipiscing elit. Morbi ultrices enim diam, sit amet tincidunt eros aliquam in. Nulla euismod dolor in orci commodo posuere sit amet eget elit. Duis dapibus lobortis ex in mattis. Integer quis nisi et metus efficitur tempor ut ut lectus. Praesent ac iaculis enim, sit amet tristique metus. Quisque vel neque quis erat cursus iaculis id id ante. Integer ac pharetra dui. Vivamus eleifend massa nisi, non ornare mauris vehicula ac."
            }
        ]
    },
    {
        "name": "Done",
        "cards": [
            {
                "name": "Ipsum",
                "description": "Mauris nec nisl non est maximus vehicula vestibulum et nisi. Pellentesque convallis neque at nisl varius condimentum. Curabitur laoreet semper ipsum nec lacinia. Donec gravida vel purus sit amet posuere. Aenean semper sed dolor non finibus. Aliquam a neque dolor. Nam ut mi ac nisi vestibulum sagittis at sed dolor. Nam bibendum sodales accumsan. Duis gravida, ipsum faucibus porta rhoncus, lacus risus lobortis nisi, ut mollis justo ligula at odio. Sed vel libero nulla."
            }
        ]
    }
]